littlemail.py
littlemail-0.33.dist-info/METADATA
littlemail-0.33.dist-info/WHEEL
littlemail-0.33.dist-info/licenses/LICENSE
littlemail-0.33.dist-info/RECORD
