Metadata-Version: 2.4
Name: littlemail
Version: 0.33
Summary: Command-line SMTP email sending tool in Python
Project-URL: homepage, https://github.com/xinlin-z/littlemail
Author-email: xinlin-z <xinlin.zhang@hotmail.com>
License: MIT License
License-File: LICENSE
Keywords: command line,email,python,smtp
Classifier: License :: OSI Approved :: MIT License
Classifier: Operating System :: OS Independent
Classifier: Programming Language :: Python :: 3
Requires-Python: >=3.8
